Metadata-Version: 2.1
Name: django-flexible-manifest-staticfiles
Version: 1.0.2
Summary: An extension of Django ManifestStaticFilesStorage that allows ignoring (excluding) specified files from being versioned, such as images or fonts.
Home-page: https://github.com/TomAnthony/django-flexible-manifest-staticfiles
Author: Tom Anthony
Author-email: django@tomanthony.co.uk
License: MIT
Platform: UNKNOWN
